Verilog/cla.v
// 4-Bit Carry Lookahead Adder
module cla (a, b, cin, s, c);

	// Inputs
	input [3:0] a;
	input [3:0] b;
	input cin;

	//Outputs
	output [3:0] s;
	output [3:0] c;

	// Carry Propogate and Carry Generate Stage

	// Carry Propagates p_i = a_i XOR b_i
	wire [3:0] p;
	xor P0(p[0], a[0], b[0]);
	xor P1(p[1], a[1], b[1]);
	xor P2(p[2], a[2], b[2]);
	xor P3(p[3], a[3], b[3]);

	// Carry Generates g_i = a_i AND b_i
	wire [3:0] g;
	and G0(g[0], a[0], b[0]);
	and G1(g[1], a[1], b[1]);
	and G2(g[2], a[2], b[2]);
	and G3(g[3], a[3], b[3]);

	// Carry Lookahead Stage : c_{i+1} = g_i + p_i.c_i

	wire w0, w1, w2, w3, w4, w5, w6, w7, w8, w9;

	// c1 = g0 + p0.cin
	and AND20(w0, p[0], cin);
	or  OR20 (c[0], g[0], w0);

	// c2 = g1 + p1.g0 + p1.p0.cin
	and AND21(w1, p[1], g[0]);
	and AND30(w2, p[1], p[0], Cin);
	or  OR30 (c[1], g[1], w1, w2);

	// c3 = g2 + p2.g1 + p2.p1.g0 + p2.p1.p0.cin
	and AND22(w3, p[2], g[1]);
	and AND31(w4, p[2], p[1], g[0]);
	and AND40(w5, p[2], p[1], p[0], cin);
	or  OR40 (c[2], g[2], w3, w4, w5);

	// c4 = g3 + p3.g2 + p3.p2.g1 + p3.p2.p1.g0 + p3.p2.p1.p0.cin
	and AND23(w6, p[3], g[2]);
	and AND32(w7, p[3], p[2], g[1]);
	and AND41(w8, p[3], p[2], p[1], g[0]);
	and AND50(w9, p[3], p[2], p[1], p[0], cin);
	or  OR50 (c[3], g[3], w6, w7, w8, w9);

	// Sum Stage : s_i = p_i XOR c_i
	xor S0(s[0], p[0], cin);
	xor S1(s[1], p[1], c[0]);
	xor S2(s[2], p[2], c[1]);
	xor S3(s[3], p[3], c[2]);

endmodule

Verilog/testbench.v
`timescale 1ns/1ps
module testbench();
	reg [3:0] a;
	reg [3:0] b;
	reg cin;

	output [3:0] s;
	output [3:0] c;

	cla X(a, b, cin, s, c);

	initial begin
		$dumpfile("cla.vcd");
		$dumpvars(0,testbench);

		$monitor($time, " a = %d, b = %d, cin = %d, carry = %d, sum = %d", a, b, cin, c[3], s);
		a = 4'd0; b = 4'd0; cin = 1'd0;

		#20 a = 4'd6; b = 4'd2; cin = 0;
		#20 a = 4'd3; b = 4'd10; cin = 0;
		#20 a = 4'd11; b = 4'd10; cin = 1;
		#20 a = 4'd0; b = 4'd0; cin = 0;
		#20 a = 4'd9; b = 4'd0; cin = 1;
		#20 a = 4'd15; b = 4'd15; cin = 1;
		#20 a = 4'd6; b = 4'd2; cin = 0;
		
		$finish;
	end
endmodule

Verilog/cla.vcd
$date
	Tue Dec  7 11:39:25 2021
$end
$version
	Icarus Verilog
$end
$timescale
	1ps
$end
$scope module testbench $end
$var wire 4 ! s [3:0] $end
$var wire 4 " c [3:0] $end
$var reg 4 # a [3:0] $end
$var reg 4 $ b [3:0] $end
$var reg 1 % cin $end
$scope module X $end
$var wire 1 & Cin $end
$var wire 4 ' a [3:0] $end
$var wire 4 ( b [3:0] $end
$var wire 1 % cin $end
$var wire 1 ) w0 $end
$var wire 1 * w1 $end
$var wire 1 + w2 $end
$var wire 1 , w3 $end
$var wire 1 - w4 $end
$var wire 1 . w5 $end
$var wire 1 / w6 $end
$var wire 1 0 w7 $end
$var wire 1 1 w8 $end
$var wire 1 2 w9 $end
$var wire 4 3 s [3:0] $end
$var wire 4 4 p [3:0] $end
$var wire 4 5 g [3:0] $end
$var wire 4 6 c [3:0] $end
$upscope $end
$upscope $end
$enddefinitions $end
#0
$dumpvars
b0 6
b0 5
b0 4
b0 3
02
01
00
0/
0.
0-
0,
0+
0*
0)
b0 (
b0 '
z&
0%
b0 $
b0 #
b0 "
b0 !
$end
#20000
b1000 !
b1000 3
b110 "
b110 6
1,
b100 4
b10 5
b10 $
b10 (
b110 #
b110 '
#40000
b10 "
b10 6
0,
b1101 !
b1101 3
b1001 4
b1010 $
b1010 (
b11 #
b11 '
#60000
b1011 "
b1011 6
b1 4
b1010 5
1)
b110 !
b110 3
1%
b1011 #
b1011 '
#80000
b0 "
b0 6
b0 4
b0 5
0)
b0 !
b0 3
0%
b0 $
b0 (
b0 #
b0 '
#100000
b1 "
b1 6
1)
b1001 4
b1010 !
b1010 3
1%
b1001 #
b1001 '
#120000
0)
b1111 !
b1111 3
b1111 "
b1111 6
b0 4
b1111 5
b1111 $
b1111 (
b1111 #
b1111 '
#140000
1,
b110 "
b110 6
b100 4
b10 5
b1000 !
b1000 3
0%
b10 $
b10 (
b110 #
b110 '
